discotify/__init__.py
discotify/discotify.py
discotify/main.py
discotify-1.0.0.dist-info/licenses/LICENSE
discotify-1.0.0.dist-info/METADATA
discotify-1.0.0.dist-info/WHEEL
discotify-1.0.0.dist-info/entry_points.txt
discotify-1.0.0.dist-info/top_level.txt
discotify-1.0.0.dist-info/RECORD
