Metadata-Version: 2.4
Name: discotify
Version: 1.0.0
Summary: Send Discord Notifications from shell or python. You can use system saved aliases for the webhook and userIDs
Author-email: Yavor Vidolov <yavorvvv@gmail.com>
License: MIT
Project-URL: Homepage, https://github.com/yvvidolov/discotify
Project-URL: Repository, https://github.com/yvvidolov/discotify.git
Project-URL: Issues, https://github.com/yvvidolov/discotify/issues
Requires-Python: >=3.7
License-File: LICENSE
Requires-Dist: requests
Provides-Extra: dev
Requires-Dist: pytest>=6.0; extra == "dev"
Requires-Dist: pytest-cov; extra == "dev"
Requires-Dist: mypy; extra == "dev"
Dynamic: license-file
